{
  "name": "hello-friend",
  "description": "This is a cool demo image",
  "image_name": "jaiminrathod98765/i7",
  "author": "Gopay System Automation Team",
  "contributors": "",
  "organization": "gopay-systems",
  "authorized_groups": [
    "demo-group"
  ],
  "env_vars": {
    "secrets": [{
      "name": "TOP_SECRET_1",
      "description": "Secret"
    },
      {
        "name": "TOP_SECRET_2",
        "description": "[Mandatory] Base64 KUBECONFIG_GOKU_STAGING"
      }
    ],
    "args": [{
        "name": "name",
        "description": "[Mandatory] Your name",
        "required" : true
      },
      {
        "name": "surname",
        "description": "[Mandatory] Your surname",
        "required": true
      }
    ]
  }
}
